marEx/__init__.py
marEx/_coverage_init.py
marEx/_dependencies.py
marEx/detect.py
marEx/exceptions.py
marEx/helper.py
marEx/logging_config.py
marEx/track.py
marEx/plotX/__init__.py
marEx/plotX/base.py
marEx/plotX/gridded.py
marEx/plotX/unstructured.py
marex-4.0.3.dist-info/METADATA
marex-4.0.3.dist-info/WHEEL
marex-4.0.3.dist-info/top_level.txt
marex-4.0.3.dist-info/RECORD
