Metadata-Version: 2.4
Name: marEx
Version: 4.0.3
Summary: Marine Extremes Detection and Tracking
Author-email: Aaron Wienkers <aaron@wienkers.com>
Project-URL: Homepage, https://github.com/wienkers/marEx
Project-URL: Bug Tracker, https://github.com/wienkers/marEx/issues
Classifier: Development Status :: 5 - Production/Stable
Classifier: Intended Audience :: Science/Research
Classifier: Topic :: Scientific/Engineering :: Atmospheric Science
Classifier: Topic :: Scientific/Engineering :: Physics
Classifier: Programming Language :: Python :: 3
Classifier: Programming Language :: Python :: 3.10
Classifier: Programming Language :: Python :: 3.11
Classifier: Programming Language :: Python :: 3.12
Classifier: Operating System :: OS Independent
Classifier: Operating System :: POSIX :: Linux
Classifier: Operating System :: MacOS
Classifier: Operating System :: Microsoft :: Windows
Requires-Python: >=3.10
Requires-Dist: numpy
Requires-Dist: xarray[complete]
Requires-Dist: dask[complete]==2025.3.0
Requires-Dist: netcdf4
Requires-Dist: scipy
Requires-Dist: scikit-image
Requires-Dist: dask_image
Requires-Dist: pandas
Requires-Dist: numba
Requires-Dist: pillow
Requires-Dist: xhistogram
Requires-Dist: flox>=0.10.1
Requires-Dist: matplotlib
Requires-Dist: cartopy
Provides-Extra: minimal
Provides-Extra: performance
Requires-Dist: jax; extra == "performance"
Requires-Dist: jaxlib; extra == "performance"
Provides-Extra: hpc
Requires-Dist: dask_jobqueue; extra == "hpc"
Requires-Dist: psutil; extra == "hpc"
Provides-Extra: plotting
Requires-Dist: seaborn>=0.11.0; extra == "plotting"
Requires-Dist: cmocean; extra == "plotting"
Requires-Dist: cartopy; extra == "plotting"
Requires-Dist: matplotlib>=3.5.0; extra == "plotting"
Requires-Dist: ffmpeg; extra == "plotting"
Provides-Extra: full
Requires-Dist: jax; extra == "full"
Requires-Dist: jaxlib; extra == "full"
Requires-Dist: dask_jobqueue; extra == "full"
Requires-Dist: seaborn>=0.11.0; extra == "full"
Requires-Dist: cmocean; extra == "full"
Requires-Dist: ffmpeg; extra == "full"
Provides-Extra: dev
Requires-Dist: pytest>=7.0.0; extra == "dev"
Requires-Dist: pytest-cov; extra == "dev"
Requires-Dist: pytest-xdist; extra == "dev"
Requires-Dist: black>=22.0.0; extra == "dev"
Requires-Dist: flake8>=4.0.0; extra == "dev"
Requires-Dist: flake8-pyproject; extra == "dev"
Requires-Dist: isort>=5.0.0; extra == "dev"
Requires-Dist: mypy>=0.991; extra == "dev"
Requires-Dist: pre-commit>=2.20.0; extra == "dev"
Requires-Dist: coverage[toml]>=6.0.0; extra == "dev"
Requires-Dist: nbqa; extra == "dev"
Requires-Dist: bandit[toml]>=1.7.0; extra == "dev"
Requires-Dist: psutil; extra == "dev"
Requires-Dist: sphinx>=5.0.0; extra == "dev"
Requires-Dist: sphinx-rtd-theme; extra == "dev"
Requires-Dist: myst-parser; extra == "dev"
Requires-Dist: jupyter; extra == "dev"
Requires-Dist: ipykernel; extra == "dev"
Provides-Extra: docs
Requires-Dist: sphinx>=5.0.0; extra == "docs"
Requires-Dist: sphinx-rtd-theme; extra == "docs"
Requires-Dist: myst-parser; extra == "docs"
Requires-Dist: sphinx-autodoc-typehints; extra == "docs"
Requires-Dist: nbsphinx; extra == "docs"
Requires-Dist: pandoc; extra == "docs"
Requires-Dist: sphinxcontrib-video; extra == "docs"
Provides-Extra: test
Requires-Dist: pytest>=7.0.0; extra == "test"
Requires-Dist: pytest-cov; extra == "test"
Requires-Dist: pytest-xdist; extra == "test"
Requires-Dist: coverage[toml]>=6.0.0; extra == "test"
Requires-Dist: psutil; extra == "test"
